{
  "patients": [
    {
      "id": "1",
      "name": "Ana Silva",
      "cpf": "123.456.789-00",
      "age": 65,
      "gender": "female",
      "weight": 68,
      "height": 1.65,
      "calf": 32,
      "phone": "(11) 99999-0000",
      "clinic": "Unidade A",
      "lastEvaluation": "08/05/2026",
      "updatedAt": "2026-05-08"
    },
    {
      "id": "2",
      "name": "João Souza",
      "cpf": "987.654.321-00",
      "age": 72,
      "gender": "male",
      "weight": 82,
      "height": 1.72,
      "calf": 35,
      "phone": "(11) 98888-0000",
      "clinic": "Unidade B",
      "lastEvaluation": "Sem avaliação",
      "updatedAt": "2026-05-08"
    },
    {
      "id": "1778232889811-65",
      "name": "Palet Deot",
      "cpf": "719.255.951-29",
      "age": 60,
      "gender": "male",
      "weight": 72,
      "height": 1.7,
      "calf": 34,
      "phone": "",
      "clinic": "",
      "lastEvaluation": "08/05/2026",
      "updatedAt": "2026-05-08"
    },
    {
      "id": "1778234118237-116",
      "name": "Loid Padre",
      "cpf": "719.255.951-30",
      "birthDate": "",
      "gender": "male",
      "phone": "",
      "clinic": ""
    },
    {
      "id": "1778235921360-26",
      "name": "Nelson José",
      "cpf": "719.255.951-44",
      "birthDate": "",
      "gender": "male",
      "phone": "",
      "clinic": ""
    },
    {
      "id": "1778236063179-371",
      "name": "Nelson José",
      "cpf": "719.255.951-44",
      "birthDate": "",
      "gender": "male",
      "phone": "",
      "clinic": ""
    },
    {
      "id": "1778236551793-225",
      "name": "Meury Paulo",
      "cpf": "719.255.951-22",
      "birthDate": "",
      "gender": "female",
      "phone": "",
      "clinic": ""
    },
    {
      "id": "1778236631261-328",
      "name": "Mikail weng",
      "cpf": "719.255.951-30",
      "birthDate": "",
      "gender": "male",
      "phone": "",
      "clinic": ""
    },
    {
      "id": "1778237044122-873",
      "name": "Nengue Pro",
      "cpf": "719.255.951-22",
      "birthDate": "",
      "gender": "male",
      "phone": "",
      "clinic": ""
    },
    {
      "id": "1778252784815-442",
      "name": "Palet Deot",
      "cpf": "719.255.951-30",
      "birthDate": "",
      "gender": "male",
      "phone": "",
      "clinic": ""
    },
    {
      "id": "1778253119630-406",
      "name": "Palet Deot",
      "cpf": "719.255.951-44",
      "birthDate": "",
      "gender": "male",
      "phone": "",
      "clinic": ""
    },
    {
      "id": "1778255719223-617",
      "name": "Mikail SAn",
      "cpf": "719.255.951-11",
      "birthDate": "",
      "gender": "male",
      "phone": "",
      "clinic": ""
    },
    {
      "id": "1778255859401-303",
      "name": "Jony dos Santos",
      "cpf": "719.255.951-24",
      "birthDate": "",
      "gender": "male",
      "phone": "",
      "clinic": ""
    },
    {
      "id": "1778255859432-685",
      "name": "Jony dos Santos",
      "cpf": "719.255.951-24",
      "birthDate": "",
      "gender": "male",
      "phone": "",
      "clinic": ""
    },
    {
      "id": "1778871215989-243",
      "name": "Mikhail Francisco",
      "cpf": "120.272.231-17",
      "birthDate": "",
      "gender": "male",
      "phone": "",
      "clinic": "",
      "age": 25,
      "weight": 90,
      "height": 1.68,
      "calf": 30,
      "lastEvaluation": "Sem avaliação",
      "updatedAt": "2026-05-15"
    },
    {
      "id": "1778871913360-917",
      "name": "Mikhail Eduardo",
      "cpf": "120.272.231-77",
      "birthDate": "",
      "gender": "male",
      "phone": "",
      "clinic": "",
      "age": 25,
      "weight": 90,
      "height": 1.7,
      "calf": 30,
      "lastEvaluation": "Sem avaliação",
      "updatedAt": "2026-05-15"
    }
  ],
  "evaluations": [
    {
      "id": "101",
      "patientName": "Ana Silva",
      "patientCpf": "123.456.789-00",
      "date": "01/05/2026",
      "diagnosis": "Sarcopenia Confirmada",
      "professional": "Dra. Maria",
      "status": "Realizado"
    },
    {
      "id": "1778232837199-424",
      "patientName": "Ana Silva",
      "patientCpf": "123.456.789-00",
      "diagnosis": "Provável Sarcopenia",
      "date": "08/05/2026",
      "professional": "Sistema",
      "status": "Realizado"
    },
    {
      "id": "1778232976592-501",
      "patientName": "Palet Deot",
      "patientCpf": "719.255.951-29",
      "diagnosis": "Sem Sarcopenia",
      "date": "08/05/2026",
      "professional": "Sistema",
      "status": "Realizado"
    },
    {
      "id": "1778233237147-878",
      "patientName": "Ana Silva",
      "patientCpf": "123.456.789-00",
      "diagnosis": "Provável Sarcopenia",
      "date": "08/05/2026",
      "professional": "Sistema",
      "status": "Realizado"
    },
    {
      "id": "1778233937248-215",
      "patientName": "Ana Silva",
      "patientCpf": "123.456.789-00",
      "diagnosis": "Sarcopenia Confirmada",
      "date": "08/05/2026",
      "professional": "Sistema",
      "status": "Realizado"
    },
    {
      "id": "1778234446003-246",
      "patientName": "Ana Silva",
      "patientCpf": "123.456.789-00",
      "diagnosis": "Provável Sarcopenia",
      "date": "08/05/2026",
      "professional": "Sistema",
      "status": "Realizado"
    },
    {
      "id": "1778257970454-519",
      "patientName": "Ana Silva",
      "patientCpf": "123.456.789-00",
      "diagnosis": "Provável Sarcopenia",
      "date": "08/05/2026",
      "professional": "Sistema",
      "status": "Realizado"
    }
  ]
}